{
  "db_name": "SQLite",
  "query": "SELECT album_id as \"album_id!: Uuid\", artist_id as \"artist_id!: Uuid\"\n           FROM album_artists\n           ORDER BY album_id, ordering",
  "describe": {
    "columns": [
      {
        "name": "album_id!: Uuid",
        "ordinal": 0,
        "type_info": "Blob"
      },
      {
        "name": "artist_id!: Uuid",
        "ordinal": 1,
        "type_info": "Blob"
      }
    ],
    "parameters": {
      "Right": 0
    },
    "nullable": [
      false,
      false
    ]
  },
  "hash": "3694a9b5a504e158e06c0d87f05bfff50582562344661ed72f1915b06c1713c5"
}
